<updates>
    <update>
        <name>Quick Admin Navigation for Joomla 4</name>
        <version>1.0.1</version>
        <element>mod_quickadminnav</element>
        <type>module</type>
        <client>administrator</client>
        <folder />
        <infourl title="Quickadminnav for Joomla 4. 1.0.1">https://github.com/johnpitchers/Quick-Admin-Navigation-for-Joomla-4.git</infourl>
        <downloads>
            <downloadurl type="full" format="zip">https://raw.githubusercontent.com/johnpitchers/Quick-Admin-Navigation-for-Joomla-4/main/mod_quickadminnav_1.0.1.zip</downloadurl>
        </downloads>
        <tags>
            <tag>stable</tag>
        </tags>
        <targetplatform name="joomla" version="4.[01]"/>
        <php_minimum>7.2</php_minimum>
    </update>
</updates>
